[
  {
    "date": "2026-06-22",
    "count": 21934
  },
  {
    "date": "2026-06-23",
    "count": 21985
  },
  {
    "date": "2026-06-24",
    "count": 22019
  },
  {
    "date": "2026-06-25",
    "count": 22071
  },
  {
    "date": "2026-06-26",
    "count": 22087
  },
  {
    "date": "2026-06-27",
    "count": 22081
  },
  {
    "date": "2026-06-28",
    "count": 22200
  },
  {
    "date": "2026-06-29",
    "count": 22267
  },
  {
    "date": "2026-06-30",
    "count": 22276
  },
  {
    "date": "2026-07-01",
    "count": 22304
  },
  {
    "date": "2026-07-02",
    "count": 22314
  },
  {
    "date": "2026-07-03",
    "count": 22331
  },
  {
    "date": "2026-07-04",
    "count": 22344
  },
  {
    "date": "2026-07-05",
    "count": 22350
  },
  {
    "date": "2026-07-06",
    "count": 22345
  },
  {
    "date": "2026-07-07",
    "count": 22324
  },
  {
    "date": "2026-07-08",
    "count": 22307
  },
  {
    "date": "2026-07-09",
    "count": 22293
  },
  {
    "date": "2026-07-10",
    "count": 22306
  },
  {
    "date": "2026-07-11",
    "count": 22326
  },
  {
    "date": "2026-07-12",
    "count": 22323
  },
  {
    "date": "2026-07-13",
    "count": 22331
  }
]